pgeon/__init__.py
pgeon/agent.py
pgeon/discretizer.py
pgeon/environment.py
pgeon/policy_graph.py
pgeon_xai-1.0.1.dist-info/METADATA
pgeon_xai-1.0.1.dist-info/WHEEL
pgeon_xai-1.0.1.dist-info/licenses/LICENSE
pgeon_xai-1.0.1.dist-info/RECORD
