Metadata-Version: 2.1
Name: pgeon-xai
Version: 1.0.1
Summary: pgeon (or pgeon-xai) is a Python package that produces explanations for opaque agents using Policy Graphs (PGs)
Project-URL: Homepage, https://github.com/HPAI-BSC/pgeon
Project-URL: Repository, https://github.com/HPAI-BSC/pgeon
Project-URL: Bug Tracker, https://github.com/HPAI-BSC/pgeon/issues
Author-email: Adrian Tormos <hpai@bsc.es>, Victor Gimenez-Abalos <hpai@bsc.es>, Dmitry Gnatyshak <hpai@bsc.es>, Sergio Alvarez-Napagao <hpai@bsc.es>
Maintainer-email: Adrian Tormos <hpai@bsc.es>, Sergio Alvarez-Napagao <hpai@bsc.es>
License: Copyright (c) 2023, 2024 Adrian Tormos, Victor Gimenez-Abalos, Dmitry Gnatyshak,
License-File: LICENSE
Keywords: agents,artificial intelligence,explainability,policy graphs,reinforcement learning
Classifier: Development Status :: 5 - Production/Stable
Classifier: License :: OSI Approved :: MIT License
Classifier: Programming Language :: Python
Requires-Python: >=3.8
Requires-Dist: gymnasium
Requires-Dist: gymnasium[classic-control]
Requires-Dist: jupyter
Requires-Dist: networkx>=3.1
Requires-Dist: numpy>=1.24.4
Requires-Dist: ray[rllib]>=2.8.1
Requires-Dist: torch
Requires-Dist: tqdm>=4.66.1
